{
  "generated_by": "assistant",
  "generated_at": "2025-11-03T12:00:00Z",
  "notes": "This file records which services are used by the codebase, their env var names, whether they are required, and last-known test status. It DOES NOT contain secret values.",
  "services": [
    {
      "name": "CoinGecko",
      "env_var": "COINGECKO_API_KEY",
      "required": false,
      "tested": true,
      "status": "ok",
      "note": "Client falls back to public API when key not present. Tested via scripts/test_external_apis.py ping."
    },
    {
      "name": "AlphaVantage",
      "env_var": "ALPHAVANTAGE_API_KEY",
      "required": true,
      "tested": true,
      "status": "ok",
      "note": "Used by certus.ingest.alphavantage_client.global_quote. Tested."
    },
    {
      "name": "Finnhub",
      "env_var": "FINNHUB_API_KEY",
      "required": true,
      "tested": true,
      "status": "ok",
      "note": "Used by certus.ingest.finnhub_client.quote. Tested."
    },
    {
      "name": "Cryptopanic",
      "env_var": "CRYPTOPANIC_API_KEY",
      "required": true,
      "tested": true,
      "status": "ok",
      "note": "Used by certus.ingest.cryptopanic.latest_posts. Tested."
    },
    {
      "name": "CoinMarketCal",
      "env_var": "COINMARKETCAL_API_KEY",
      "required": true,
      "tested": true,
      "status": "ok",
      "note": "Used by certus.ingest.coinmarketcal.fetch_events. Tested."
    },
    {
      "name": "CoinMarketCap",
      "env_var": "COINMARKETCAP_API_KEY",
      "required": false,
      "tested": false,
      "status": "untested",
      "note": "Not currently used by codebase; credential provided by user but not tested."
    },
    {
      "name": "Binance",
      "env_var": "BINANCE_API_KEY",
      "required": false,
      "tested": false,
      "status": "untested",
      "note": "Not currently used by codebase."
    },
    {
      "name": "Alpaca",
      "env_var": "ALPACA_KEY",
      "required": false,
      "tested": false,
      "status": "untested",
      "note": "Not currently used by codebase. If you want this tested, provide the exact env var names and whether key/secret pair are needed."
    },
    {
      "name": "Polygon",
      "env_var": "POLYGON_API_KEY",
      "required": false,
      "tested": false,
      "status": "untested",
      "note": "Not currently used by codebase."
    },
    {
      "name": "Telegram Bot",
      "env_var": "TELEGRAM_BOT_TOKEN",
      "required": false,
      "tested": false,
      "status": "untested",
      "note": "Can be tested via getMe endpoint if desired."
    }
  ]
  ,
  "last_test_run": {
    "tested_at": "2025-11-03T12:00:00Z",
    "summary": [
      {"name": "CoinGecko", "status": "ok"},
      {"name": "AlphaVantage", "status": "ok"},
      {"name": "Finnhub", "status": "ok"},
      {"name": "Cryptopanic", "status": "ok"},
      {"name": "CoinMarketCal", "status": "ok"}
    ],
    "note": "Tests run by assistant using transient environment variables provided by user; no secrets were stored in the repo."
  }
}
